<?xml version="1.0" encoding="UTF-8"?>
<silverpeas-settings product="Silverpeas">
  <global-vars>
    <var name="DB_SERVERTYPEU" value='$eval{{value=new String("${DB_SERVERTYPE}").toUpperCase();}}'/>
    <var name="DB_DRIVER_MSSQL" value="net.sourceforge.jtds.jdbc.Driver"/>
    <var name="DB_DRIVER_H2" value="org.h2.Driver"/>
    <var name="DB_DRIVER_ORACLE" value="oracle.jdbc.driver.OracleDriver"/>
    <var name="DB_DRIVER_POSTGRES" value="org.postgresql.Driver"/>
    <var name="DB_DRIVER" value='$eval{{if(new String("${DB_SERVERTYPEU}").equals("MSSQL")) value="${DB_DRIVER_MSSQL}"; else if(new String("${DB_SERVERTYPEU}").equals("POSTGRES")) value="${DB_DRIVER_POSTGRES}"; else if(new String("${DB_SERVERTYPEU}").equals("H2")) value="${DB_DRIVER_H2}"; else value="${DB_DRIVER_ORACLE}";}}'/>

    <var name="XA_DRIVER_MSSQL" value="net.sourceforge.jtds.jdbcx.JtdsDataSource"/>
    <var name="XA_DRIVER_H2" value="org.h2.jdbcx.JdbcDataSource"/>
    <var name="XA_DRIVER_ORACLE" value="oracle.jdbc.xa.client.OracleXADataSource"/>
    <var name="XA_DRIVER_POSTGRES" value="org.postgresql.xa.PGXADataSource"/>
    <var name="XA_DRIVER" value='$eval{{if(new String("${DB_SERVERTYPEU}").equals("MSSQL")) value="${XA_DRIVER_MSSQL}"; else if(new String("${DB_SERVERTYPEU}").equals("POSTGRES")) value="${XA_DRIVER_POSTGRES}"; else if(new String("${DB_SERVERTYPEU}").equals("H2")) value="${XA_DRIVER_H2}"; else value="${XA_DRIVER_ORACLE}";}}'/>

    <var name="SQL_LISTEN_PORT" value='$eval{{if(new String("${DB_SERVERTYPEU}").equals("MSSQL")) value="${SQL_LISTEN_PORT_MSSQL}"; else if(new String("${DB_SERVERTYPEU}").equals("POSTGRES")) value="${SQL_LISTEN_PORT_POSTGRES}"; else if(new String("${DB_SERVERTYPEU}").equals("H2")) value="${SQL_LISTEN_PORT_H2}"; else value="${SQL_LISTEN_PORT_ORACLE}";}}'/>
    <var name="DB_URL_MSSQL" value="jdbc:jtds:sqlserver://${DB_SERVER}:${SQL_LISTEN_PORT}/${DB_NAME}"/>
    <var name="DB_URL_ORACLE" value="jdbc:oracle:thin:@${DB_SERVER}:${SQL_LISTEN_PORT}:${DB_NAME}"/>
    <var name="DB_URL_POSTGRES" value="jdbc:postgresql://${DB_SERVER}:${SQL_LISTEN_PORT}/${DB_NAME}"/>
    <var name="DB_URL_H2" value="jdbc:h2:tcp://${DB_SERVER}:${SQL_LISTEN_PORT}/${DB_NAME}"/>
    <var name="DB_URL" value='$eval{{if(new String("${DB_SERVERTYPEU}").equals("MSSQL")) value="${DB_URL_MSSQL}"; else if(new String("${DB_SERVERTYPEU}").equals("POSTGRES")) value="${DB_URL_POSTGRES}"; else if(new String("${DB_SERVERTYPEU}").equals("H2")) value="${DB_URL_H2}";else value="${DB_URL_ORACLE}";}}'/>

    <var name="HIBERNATE_DIALECT_MSSQL" value="org.hibernate.dialect.SQLServerDialect"/>
    <var name="HIBERNATE_DIALECT_H2" value="org.hibernate.dialect.H2Dialect"/>
    <var name="HIBERNATE_DIALECT_ORACLE" value="org.hibernate.dialect.OracleDialect"/>
    <var name="HIBERNATE_DIALECT_POSTGRES" value="org.hibernate.dialect.PostgreSQLDialect"/>
    <var name="HIBERNATE_DIALECT" value='$eval{{if(new String("${DB_SERVERTYPEU}").equals("MSSQL")) value="${HIBERNATE_DIALECT_MSSQL}"; else if(new String("${DB_SERVERTYPEU}").equals("POSTGRES")) value="${HIBERNATE_DIALECT_POSTGRES}"; else if(new String("${DB_SERVERTYPEU}").equals("H2")) value="${HIBERNATE_DIALECT_H2}"; else value="${HIBERNATE_DIALECT_ORACLE}";}}'/>

    <var name="JACKRABBIT_PERSIST_H2" value="org.apache.jackrabbit.core.persistence.pool.H2PersistenceManager"/>
    <var name="JACKRABBIT_PERSIST_MSSQL" value="org.apache.jackrabbit.core.persistence.pool.MSSqlPersistenceManager"/>
    <var name="JACKRABBIT_PERSIST_ORACLE" value="org.apache.jackrabbit.core.persistence.pool.OraclePersistenceManager"/>
    <var name="JACKRABBIT_PERSIST_POSTGRES" value="org.apache.jackrabbit.core.persistence.pool.PostgreSQLPersistenceManager"/>
    <var name="JACKRABBIT_PERSIST" value='$eval{{if(new String("${DB_SERVERTYPEU}").equals("MSSQL")) value="${JACKRABBIT_PERSIST_MSSQL}"; else if(new String("${DB_SERVERTYPEU}").equals("POSTGRES")) value="${JACKRABBIT_PERSIST_POSTGRES}"; else if(new String("${DB_SERVERTYPEU}").equals("H2")) value="${JACKRABBIT_PERSIST_H2}";else value="${JACKRABBIT_PERSIST_ORACLE}";}}'/>

    <var name="JACKRABBIT_SCHEMA_H2" value="h2"/>
    <var name="JACKRABBIT_SCHEMA_MSSQL" value="mssql"/>
    <var name="JACKRABBIT_SCHEMA_ORACLE" value="oracle"/>
    <var name="JACKRABBIT_SCHEMA_POSTGRES" value="postgresql"/>
    <var name="JACKRABBIT_SCHEMA" value='$eval{{if(new String("${DB_SERVERTYPEU}").equals("MSSQL")) value="${JACKRABBIT_SCHEMA_MSSQL}"; else if(new String("${DB_SERVERTYPEU}").equals("POSTGRES")) value="${JACKRABBIT_SCHEMA_POSTGRES}"; else if(new String("${DB_SERVERTYPEU}").equals("H2")) value="${JACKRABBIT_SCHEMA_H2}";else value="${JACKRABBIT_SCHEMA_ORACLE}";}}'/>

    <!-- INSTALLED DIRECTORIES -->
    <var name="JAR_HOME" value="${SILVERPEAS_HOME}/jar"/>
    <var name="TEMP_HOME" value="${SILVERPEAS_DATA_HOME}/temp"/>
    <var name="LOG_HOME" value="${SILVERPEAS_HOME}/log"/>

    <var name="HIDDEN_SILVERPEAS_DIR" value="${SILVERPEAS_DATA_HOME}/.silverpeas"/>
  </global-vars>

  <script name="setupSilverpeas.groovy"/>
  <script name="updateJCRWorkspaceConfig.groovy"/>
   <script name="configureJCRMigrationConfig.groovy"/>

  <!-- PROPERTIES CONFIGURATION -->
  <fileset root="${SILVERPEAS_HOME}/initialize/">
    <configfile name="systemSettings.properties">
      <parameter key="http.proxyHost">${PROXY_HOST}</parameter>
      <parameter key="http.proxyPort">${PROXY_PORT}</parameter>
      <parameter key="http.nonProxyHosts">${NONPROXY_HOST}</parameter>
      <parameter key="ftp.proxyHost">${PROXY_HOST}</parameter>
      <parameter key="ftp.proxyPort">${PROXY_PORT}</parameter>
      <parameter key="ftp.nonProxyHosts">${NONPROXY_HOST}</parameter>
    </configfile>
  </fileset>
  
  <fileset root="${SILVERPEAS_HOME}/properties/org/silverpeas/">

    <configfile name="util/jcr.properties">
      <parameter key="jcr.configuration.persistence.manager">${JACKRABBIT_PERSIST}</parameter>
      <parameter key="jcr.home.dir.url">file:///${SILVERPEAS_DATA_HOME}/jackrabbit</parameter>
      <parameter key="schema">${JACKRABBIT_SCHEMA}</parameter>
    </configfile>

    <configfile name="general.properties">
      <parameter key="ApplicationURL">/silverpeas</parameter>
      <parameter key="uploadsPath">${SILVERPEAS_DATA_HOME}/workspaces</parameter>
      <parameter key="uploadsIndexPath">${SILVERPEAS_DATA_HOME}/index</parameter>
      <parameter key="tempPath">${TEMP_HOME}</parameter>
      <parameter key="exportTemplatePath">${SILVERPEAS_DATA_HOME}/template-export</parameter>
      <parameter key="securityPath">${HIDDEN_SILVERPEAS_DIR}</parameter>
    </configfile>

    <configfile name="beans/admin/admin.properties">
      <parameter key="AdminDBDriver">${DB_DRIVER}</parameter>
      <parameter key="WaProductionDb">${DB_URL}</parameter>
      <parameter key="WaProductionUser">${DB_USER}</parameter>
      <parameter key="WaProductionPswd">${DB_PASSWD}</parameter>
      <parameter key="WaAdminDb">${DB_URL}</parameter>
      <parameter key="WaAdminUser">${DB_USER}</parameter>
      <parameter key="WaAdminPswd">${DB_PASSWD}</parameter>
      <parameter key="AdministratorLogin">${ADMIN_LOGIN}</parameter>
      <parameter key="AdministratorPassword">${ADMIN_PASSWD}</parameter>
      <parameter key="AdministratorEMail">${ADMIN_EMAIL}</parameter>
      <parameter key="EntrepriseClientSpaceId">1</parameter>
      <parameter key="xmlSpaceTemplate">${SILVERPEAS_HOME}/xmlspacetemplates</parameter>
    </configfile>

    <configfile name="beans/admin/instance/control/instanciator.properties">
      <parameter key="xmlPackage">${SILVERPEAS_HOME}/xmlcomponents</parameter>
    </configfile>

    <configfile name="kmelia/settings/kmeliaSettings.properties">
      <parameter key="templatePath">${SILVERPEAS_HOME}/resources/StringTemplates/components/kmelia/</parameter>
      <parameter key="customersTemplatePath">${SILVERPEAS_DATA_HOME}/StringTemplates/components/kmelia/</parameter>
    </configfile>

    <configfile name="survey/surveySettings.properties">
      <parameter key="templatePath">${SILVERPEAS_HOME}/resources/StringTemplates/components/survey/</parameter>
      <parameter key="customersTemplatePath">${SILVERPEAS_DATA_HOME}/StringTemplates/components/survey/</parameter>
    </configfile>

    <configfile name="almanach/settings/almanachSettings.properties">
      <parameter key="templatePath">${SILVERPEAS_HOME}/resources/StringTemplates/components/almanach/</parameter>
      <parameter key="customersTemplatePath">${SILVERPEAS_DATA_HOME}/StringTemplates/components/almanach/</parameter>
    </configfile>

    <configfile name="domains/domainSP.properties">
      <parameter key="database.SQLJDBCUrl">${DB_URL}</parameter>
      <parameter key="database.SQLAccessLogin">${DB_USER}</parameter>
      <parameter key="database.SQLAccessPasswd">${DB_PASSWD}</parameter>
    </configfile>

    <configfile name="authentication/domains.properties">
      <parameter key="SQLDomainJDBCUrl">${DB_URL}</parameter>
      <parameter key="SQLDomainAccessLogin">${DB_USER}</parameter>
      <parameter key="SQLDomainAccessPasswd">${DB_PASSWD}</parameter>
      <parameter key="SQLDomainDriverClass">${DB_DRIVER}</parameter>
    </configfile>

    <configfile name="authentication/autDomainSP.properties">
      <parameter key="fallbackType">${FALLBACK_TYPE}</parameter>
      <parameter key="autServer1.SQLJDBCUrl">${DB_URL}</parameter>
      <parameter key="autServer1.SQLAccessLogin">${DB_USER}</parameter>
      <parameter key="autServer1.SQLAccessPasswd">${DB_PASSWD}</parameter>
      <parameter key="autServer1.SQLDriverClass">${DB_DRIVER}</parameter>
      <parameter key="autServer2.enabled">${NT_AUTHENT_ENABLED}</parameter>
      <parameter key="autServer2.NTRISPort">${NTRIS_PORT}</parameter>
      <parameter key="autServer2.NTRISHost">${NTRIS_SERVER}</parameter>
    </configfile>

    <configfile name="authentication/autDomainExchange2000.properties">
      <parameter key="fallbackType">${FALLBACK_TYPE}</parameter>
      <parameter key="autServer0.LDAPHost">${LDAP_SERVER}</parameter>
    </configfile>
    <configfile name="authentication/autDomainExchange55.properties">
      <parameter key="fallbackType">${FALLBACK_TYPE}</parameter>
      <parameter key="autServer0.NTRISHost">${NTRIS_HOST}</parameter>
      <parameter key="autServer0.NTRISPort">${NTRIS_PORT}</parameter>
    </configfile>

    <configfile name="authentication/autDomainLDAP.properties">
      <parameter key="fallbackType">${FALLBACK_TYPE}</parameter>
      <parameter key="autServer0.NTRISHost">${NTRIS_HOST}</parameter>
      <parameter key="autServer0.NTRISPort">${NTRIS_PORT}</parameter>
    </configfile>

    <configfile name="notificationserver/channel/smtp/smtpSettings.properties">
      <parameter key="SMTPServer">${SMTP_SERVER}</parameter>
      <parameter key="SMTPAuthentication">${SMTP_AUTHENTICATION}</parameter>
      <parameter key="SMTPDebug">${SMTP_DEBUG}</parameter>
      <parameter key="SMTPPort">${SMTP_PORT}</parameter>
      <parameter key="SMTPUser">${SMTP_USER}</parameter>
      <parameter key="SMTPPwd">${SMTP_PWD}</parameter>
      <parameter key="SMTPSecure">${SMTP_SECURE}</parameter>
    </configfile>

    <configfile name="silvertrace/settings/silverTrace.properties">
      <parameter key="pathSilverTrace">${SILVERPEAS_HOME}/silvertrace</parameter>
      <parameter key="ErrorDir">${LOG_HOME}</parameter>
      <parameter key="language">${LANGUAGE}</parameter>
    </configfile>

    <configfile name="silvertrace/settings/silverLog.properties">
      <parameter key="pathSilverLog">${SILVERPEAS_HOME}/log</parameter>
      <parameter key="LogDir">${SILVERPEAS_HOME}/log</parameter>
      <parameter key="appender0.fileName">${SILVERPEAS_HOME}/log/journal.txt</parameter>
    </configfile>

    <configfile name="_silverpeasinitialize/settings/_silverpeasinitializeSettings.properties">
      <parameter key="pathInitialize">${SILVERPEAS_HOME}/initialize</parameter>
    </configfile>

    <configfile name="dbBuilder/settings/dbBuilderSettings.properties">
      <parameter key="ADMINLOGIN">${ADMIN_LOGIN}</parameter>
      <parameter key="ADMINPASSWD">${ADMIN_PASSWD}</parameter>
      <parameter key="URLSERVER">${URL_SERVER}</parameter>
    </configfile>

    <configfile name="silverstatistics/SilverStatistics.properties">
      <parameter key="SilverPeasDataPath0">${SILVERPEAS_DATA_HOME}</parameter>
    </configfile>

    <configfile name="peasCore/SessionManager.properties">
      <parameter key="scheduledSessionManagementTimeStamp">2</parameter>
      <parameter key="userSessionTimeout">10</parameter>
    </configfile>
    
    <configfile name="infoLetter/settings/infoLetterSettings.properties">
      <parameter key="templatePath">${SILVERPEAS_HOME}/resources/StringTemplates/components/infoLetter/</parameter>
      <parameter key="customersTemplatePath">${SILVERPEAS_DATA_HOME}/StringTemplates/components/infoLetter/</parameter>
    </configfile>

    <configfile name="importExport/settings/mapping.properties">
      <parameter key="mappingDir">file:///${SILVERPEAS_HOME}/resources/importExport/</parameter>
    </configfile>

    <configfile name="questionReply/settings/questionReplySettings.properties">
      <parameter key="mappingDir">file:///${SILVERPEAS_HOME}/resources/QuestionReply/</parameter>
    </configfile>

    <configfile name="publicationTemplate/settings/mapping.properties">
      <parameter key="mappingDir">file:///${SILVERPEAS_HOME}/resources/formTemplate/</parameter>
    </configfile>

    <configfile name="publicationTemplate/settings/template.properties">
      <parameter key="templateDir">${SILVERPEAS_DATA_HOME}/templateRepository/</parameter>
    </configfile>

    <configfile name="whitePages/settings/template.properties">
      <parameter key="templateDir">file:///${SILVERPEAS_DATA_HOME}/templateRepository/</parameter>
    </configfile>

    <configfile name="jobManagerPeas/settings/jobManagerPeasSettings.properties">
      <parameter key="IsKMVisible">true</parameter>
      <parameter key="IsToolsVisible">true</parameter>
    </configfile>

    <configfile name="workflow/engine/castorSettings.properties">
      <parameter key="CastorJDOFastDatabaseFileURL">${SILVERPEAS_HOME_DEPENDANT}/resources/instanceManager/fast_database.xml</parameter>
      <parameter key="CastorJDODatabaseFileURL">${SILVERPEAS_HOME_DEPENDANT}/resources/instanceManager/database.xml</parameter>
      <parameter key="CastorJDOLogFileURL">${SILVERPEAS_HOME_DEPENDANT}/log/castor.log</parameter>
      <parameter key="CastorXMLMappingFileURL">${SILVERPEAS_HOME_DEPENDANT}/resources/modelManager/mapping.xml</parameter>
      <parameter key="ProcessModelDir">${SILVERPEAS_DATA_HOME}/workflowRepository/</parameter>
    </configfile>

    <configfile name="workflow/engine/schedulerSettings.properties">
      <parameter key="timeoutSchedule">* 0,4,8,12,16,20 * * *</parameter>
    </configfile>

    <configfile name="mailinglist/notification.properties">
      <parameter key="jdbc.driver">${DB_DRIVER}</parameter>
      <parameter key="jdbc.url">${DB_URL}</parameter>
      <parameter key="jdbc.username">${DB_USER}</parameter>
      <parameter key="jdbc.password">${DB_PASSWD}</parameter>
      <parameter key="hibernate.dialect">${HIBERNATE_DIALECT}</parameter>
    </configfile>

    <configfile name="mailinglist/settings/mailinglistSettings.properties">
      <parameter key="templatePath">${SILVERPEAS_HOME}/resources/StringTemplates/components/mailingList</parameter>
      <parameter key="customersTemplatePath">${SILVERPEAS_DATA_HOME}/resources/StringTemplates/components/mailingList</parameter>
    </configfile>
    
    <configfile name="classifieds/settings/classifiedsSettings.properties">
      <parameter key="customersTemplatePath">${SILVERPEAS_DATA_HOME}/StringTemplates/components/classifieds/</parameter>
      <parameter key="templatePath">${SILVERPEAS_HOME}/resources/StringTemplates/components/classifieds/</parameter>
    </configfile>

    <configfile name="webpages/settings/webPagesSettings.properties">
      <parameter key="customersTemplatePath">${SILVERPEAS_DATA_HOME}/StringTemplates/components/webpages/</parameter>
      <parameter key="templatePath">${SILVERPEAS_HOME}/resources/StringTemplates/components/webpages/</parameter>
    </configfile>

    <configfile name="portlets/portletsSettings.properties">
      <parameter key="portlets.configDir">${SILVERPEAS_DATA_HOME}/portlets</parameter>
    </configfile>

    <configfile name="communicationUser/settings/communicationUserSettings.properties">
      <parameter key="pathDiscussions">${SILVERPEAS_DATA_HOME}/imRepository/</parameter>
    </configfile>

    <configfile name="questionReply/settings/questionReplySettings.properties">
      <parameter key="templatePath">${SILVERPEAS_HOME}/resources/StringTemplates/components/question-reply/</parameter>
      <parameter key="customersTemplatePath">${SILVERPEAS_DATA_HOME}/StringTemplates/components/question-reply/</parameter>
    </configfile>
    
    <configfile name="whitePages/settings/template.properties">
      <parameter key="templateDir">file:///${SILVERPEAS_DATA_HOME}/templateRepository</parameter>
    </configfile>
    
    <configfile name="jobDomainPeas/settings/jobDomainPeasSettings.properties">
      <parameter key="templatePath">${SILVERPEAS_HOME}/resources/StringTemplates/</parameter>
      <parameter key="customersTemplatePath">${SILVERPEAS_DATA_HOME}/StringTemplates/</parameter>
    </configfile>

    <configfile name="jobStartPagePeas/settings/jobStartPagePeasSettings.properties">
      <parameter key="templatePath">${SILVERPEAS_HOME}/resources/StringTemplates/admin</parameter>
      <parameter key="customersTemplatePath">${SILVERPEAS_DATA_HOME}/StringTemplates/admin</parameter>
    </configfile>
       
    <configfile name="blog/settings/blogSettings.properties">
      <parameter key="templatePath">${SILVERPEAS_HOME}/resources/StringTemplates/components/blog/</parameter>
      <parameter key="customersTemplatePath">${SILVERPEAS_DATA_HOME}/StringTemplates/components/blog/</parameter>
    </configfile>
    
    <configfile name="rssAgregator/settings/rssAgregatorSettings.properties">
      <parameter key="templatePath">${SILVERPEAS_HOME}/resources/StringTemplates/components/rssaggregator/</parameter>
      <parameter key="customersTemplatePath">${SILVERPEAS_DATA_HOME}/StringTemplates/components/rssaggregator/</parameter>
    </configfile>
    
    <configfile name="delegatednews/settings/DelegatedNewsSettings.properties">
      <parameter key="templatePath">${SILVERPEAS_HOME}/resources/StringTemplates/components/delegatednews/</parameter>
      <parameter key="customersTemplatePath">${SILVERPEAS_DATA_HOME}/StringTemplates/components/delegatednews/</parameter>
    </configfile>
	
    <configfile name="components/scheduleevent/settings/ScheduleEventSettings.properties">
      <parameter key="templatePath">${SILVERPEAS_HOME}/resources/StringTemplates/components/scheduleevent/</parameter>
      <parameter key="customersTemplatePath">${SILVERPEAS_DATA_HOME}/StringTemplates/components/scheduleevent/</parameter>
    </configfile>
	
	<configfile name="util/stringtemplate.properties">
	  <parameter key="template.dir.core.default">${SILVERPEAS_HOME}/resources/StringTemplates/core</parameter>
      <parameter key="template.dir.core.custom">${SILVERPEAS_DATA_HOME}/StringTemplates/core</parameter>
      <parameter key="template.dir.components.default">${SILVERPEAS_HOME}/resources/StringTemplates/components</parameter>
      <parameter key="template.dir.components.custom">${SILVERPEAS_DATA_HOME}/StringTemplates/components</parameter> 
    </configfile>
	
	<configfile name="webSites/settings/webSiteSettings.properties">
      <parameter key="uploadsPath">${SILVERPEAS_DATA_WEB}/website.war/</parameter>
    </configfile>
	
    <configfile name="importExport/settings/importSettings.properties">
      <parameter key="importRepository">${SILVERPEAS_DATA_HOME}/import/</parameter>
    </configfile>
	
    <configfile name="util/comment/Comment.properties">
      <parameter key="customersTemplatePath">${SILVERPEAS_DATA_HOME}/StringTemplates/</parameter>
      <parameter key="templatePath">${SILVERPEAS_HOME}/resources/StringTemplates/</parameter>
    </configfile>
  
  </fileset>

  <fileset root="${SILVERPEAS_HOME}/bin/">
    <configfile name="dbBuilder.sh">
      <parameter key="SILVERPEAS_HOME">${SILVERPEAS_HOME_DEPENDANT}</parameter>
      <parameter key="SRV_SERVERTYPE">${DB_SERVERTYPE}</parameter>
      <parameter key="SILVERPEAS_DATA">${SILVERPEAS_HOME_DEPENDANT}</parameter>
    </configfile>
  </fileset>

    <!-- workflowEngine settings -->
  <fileset root="${SILVERPEAS_HOME}/resources/instanceManager/">
    <textfile name="database.xml">
      <parameter key="&lt;!DOCTYPE[^&gt;]*&gt;" use-regex="true"> </parameter>
    </textfile>

    <xmlfile name="database.xml">
      <parameter key="/jdo-conf" mode="update">
        <value location="@engine">$eval{{if(new String("${DB_SERVERTYPEU}").equals("MSSQL")) value="sql-server"; else if(new String("${DB_SERVERTYPEU}").equals("POSTGRES")) value="postgresql"; else value="oracle";}}</value>
      </parameter>
      <parameter key="/jdo-conf/database" mode="update">
        <value location="@engine">$eval{{if(new String("${DB_SERVERTYPEU}").equals("MSSQL")) value="sql-server"; else if(new String("${DB_SERVERTYPEU}").equals("POSTGRES")) value="postgresql"; else value="oracle";}}</value>
      </parameter>
      <parameter key="/jdo-conf/database/mapping" mode="update">
        <value location="@href">file:///${SILVERPEAS_HOME}/resources/instanceManager/mapping.xml</value>
      </parameter>
    </xmlfile>

    <textfile name="fast_database.xml">
      <parameter key="&lt;!DOCTYPE[^&gt;]*&gt;" use-regex="true"> </parameter>
    </textfile>

    <xmlfile name="fast_database.xml">
      <parameter key="/database" mode="update">
        <value location="@engine">$eval{{if(new String("${DB_SERVERTYPEU}").equals("MSSQL")) value="sql-server"; else if(new String("${DB_SERVERTYPEU}").equals("POSTGRES")) value="postgresql"; else value="oracle";}}</value>
      </parameter>
      <parameter key="/database/mapping" mode="update">
        <value location="@href">file:///${SILVERPEAS_HOME}/resources/instanceManager/fast_mapping.xml</value>
      </parameter>
    </xmlfile>
  </fileset>

 
  <!-- wiki -->
  <fileset root="${SILVERPEAS_HOME}/jar/silverpeas.ear/war-ic.war/WEB-INF/">
    <configfile name="jspwiki.properties">
      <parameter key="jspwiki.workDir">${SILVERPEAS_DATA_HOME}/temp/wiki/indexes</parameter>
      <parameter key="jspwiki.basicAttachmentProvider.storageDir">${SILVERPEAS_DATA_HOME}/temp/wiki/</parameter>
      <parameter key="jspwiki.fileSystemProvider.pageDir">${SILVERPEAS_DATA_HOME}/temp/wiki/pages</parameter>
    </configfile>
  </fileset>
  
  <!-- Jackrabbit -->
  <fileset root="${SILVERPEAS_HOME}/jar/silverpeas.ear/war-ic.war/WEB-INF/">
    <xmlfile name="classes/repository.xml">
      <parameter key="//Workspaces" mode="update">
        <value location="@defaultWorkspace">${webdav.workspace}</value>
      </parameter>
      <parameter key="//Workspace/PersistenceManager" mode="update">
        <value location="@class">${JACKRABBIT_PERSIST}</value>
      </parameter>
      <parameter key="//Workspace/PersistenceManager/param[@name='schema']" mode="update">
        <value location="@value">${JACKRABBIT_SCHEMA}</value>
      </parameter>
      <parameter key="//Workspace/FileSystem" mode="update">
        <value location="@class">org.apache.jackrabbit.core.fs.local.LocalFileSystem</value>
      </parameter> 
      <parameter key="//Versioning/PersistenceManager" mode="update">
        <value location="@class">${JACKRABBIT_PERSIST}</value>
      </parameter>
      <parameter key="//Versioning/PersistenceManager/param[@name='schema']" mode="update">
        <value location="@value">${JACKRABBIT_SCHEMA}</value>
      </parameter>
      <parameter key="//Versioning/FileSystem" mode="update">
        <value location="@class">org.apache.jackrabbit.core.fs.local.LocalFileSystem</value>
      </parameter> 
    </xmlfile>
  </fileset>

 <!-- Chat settings
  <fileset root="${SILVERPEAS_HOME}/properties/org/silverpeas/">
    <configfile name="chat/settings/chatSettings.properties">
      <parameter key="xmlConfigLocation">${SILVERPEAS_DATA_HOME}/chat/jchatbox.xml</parameter>
    </configfile>
  </fileset>
  <fileset root="${SILVERPEAS_DATA_HOME}/chat/">
    <textfile name="jchatbox.xml">
      <parameter key="&lt;!DOCTYPE[^&gt;]*&gt;" use-regex="true"> </parameter>
    </textfile>
    <xmlfile name="jchatbox.xml">
      <parameter key="/jChatBox/LOGFOLDER" mode="update">${SILVERPEAS_HOME}/log/chat</parameter>
    </xmlfile>
  </fileset>
  -->
  
  <script name="createTickers.groovy"/>
  <script name="updateAuthProperties.groovy"/>

</silverpeas-settings>
